xomega/__init__.py
xomega/_version.py
xomega/xomega.py
xomega/tests/__init__.py
xomega/tests/test_xomega.py
xomega-0.1.0.dist-info/LICENSE
xomega-0.1.0.dist-info/METADATA
xomega-0.1.0.dist-info/WHEEL
xomega-0.1.0.dist-info/top_level.txt
xomega-0.1.0.dist-info/RECORD
