Metadata-Version: 2.1
Name: xomega
Version: 0.1.0
Summary: Generalized Omega equation
Home-page: https://github.com/roxyboy/xomega
Author: xomega Developers
Author-email: takaya@ldeo.columbia.edu
License: MIT
Platform: UNKNOWN
Classifier: Development Status :: 4 - Beta
Classifier: License :: OSI Approved :: Apache Software License
Classifier: Operating System :: OS Independent
Classifier: Intended Audience :: Science/Research
Classifier: Programming Language :: Python
Classifier: Programming Language :: Python :: 2
Classifier: Programming Language :: Python :: 2.7
Classifier: Programming Language :: Python :: 3
Classifier: Programming Language :: Python :: 3.5
Classifier: Programming Language :: Python :: 3.6
Classifier: Topic :: Scientific/Engineering
Requires-Dist: xarray
Requires-Dist: dask
Requires-Dist: numpy
Requires-Dist: future
Requires-Dist: docrep
